UniqueBotsKR/__init__.py
UniqueBotsKR/client.py
UniqueBotsKR/errors.py
UniqueBotsKR/http.py
UniqueBotsKR/model.py
UniqueBotsKR-1.3.dist-info/LICENSE
UniqueBotsKR-1.3.dist-info/METADATA
UniqueBotsKR-1.3.dist-info/WHEEL
UniqueBotsKR-1.3.dist-info/top_level.txt
UniqueBotsKR-1.3.dist-info/RECORD
