Metadata-Version: 2.1
Name: UniqueBotsKR
Version: 1.3
Summary: UniqueBots를 위한 비공식 파이썬 API 레퍼입니다.
Home-page: https://github.com/gunyu1019/UniqueBotsKR
Author: gunyu1019
Author-email: gunyu1019@yhs.kr
License: MIT
Platform: UNKNOWN
Classifier: License :: OSI Approved :: MIT License
Classifier: Programming Language :: Python :: 3.6
Classifier: Programming Language :: Python :: 3.7
Classifier: Programming Language :: Python :: 3.8
Classifier: Programming Language :: Python :: 3.9
Requires-Python: >=3.6
Requires-Dist: aiohttp
Requires-Dist: asyncio
